odfdecrypt/__init__.py
odfdecrypt/api.py
odfdecrypt/cli.py
odfdecrypt/exceptions.py
odfdecrypt/odf_origin_detector.py
odfdecrypt/decryption/__init__.py
odfdecrypt/decryption/apache_odf_decryptor.py
odfdecrypt/decryption/base_odf_decryptor.py
odfdecrypt/decryption/libre_office_odf_decryptor.py
odfdecrypt/tests/test_api.py
odfdecrypt/tests/test_cli.py
odfdecrypt/tests/test_decryption.py
odfdecrypt/tests/test_detector.py
odfdecrypt/tests/resources/password_protected/aoo_document_pw_hello.odt
odfdecrypt/tests/resources/password_protected/aoo_drawing_pw_hello.odg
odfdecrypt/tests/resources/password_protected/aoo_formula_pw_hello.odf
odfdecrypt/tests/resources/password_protected/aoo_presentation_pw_hello.odp
odfdecrypt/tests/resources/password_protected/libre_office_drawing_pw_hello.odg
odfdecrypt/tests/resources/password_protected/libre_office_formular_pw_hello.odf
odfdecrypt/tests/resources/password_protected/libre_office_presentation_pw_hello.odp
odfdecrypt/tests/resources/password_protected/libre_office_sample_pw_hello.odt
odfdecrypt/tests/resources/password_protected/libre_office_spreadsheet_pw_hello.ods
odfdecrypt/tests/resources/plain/aoo_drawing.odg
odfdecrypt/tests/resources/plain/aoo_formula.odf
odfdecrypt/tests/resources/plain/aoo_presentation.odp
odfdecrypt/tests/resources/plain/aoo_spreadsheet.ods
odfdecrypt/tests/resources/plain/libre_office_draw.odg
odfdecrypt/tests/resources/plain/libre_office_presentation.odp
odfdecrypt/tests/resources/plain/libre_office_spreadsheet.ods
odfdecrypt-0.1.0.dist-info/METADATA
odfdecrypt-0.1.0.dist-info/WHEEL
odfdecrypt-0.1.0.dist-info/entry_points.txt
odfdecrypt-0.1.0.dist-info/licenses/LICENSE
odfdecrypt-0.1.0.dist-info/RECORD
