Metadata-Version: 2.4
Name: odfdecrypt
Version: 0.1.0
Summary: Decrypt password-protected OpenDocument Format (ODF) files from LibreOffice and Apache OpenOffice
Project-URL: Homepage, https://github.com/toobee/odf-decrypt
Project-URL: Repository, https://github.com/toobee/odf-decrypt
Project-URL: Issues, https://github.com/toobee/odf-decrypt/issues
Author: odfdecrypt contributors
Maintainer: odfdecrypt contributors
License-Expression: Apache-2.0
License-File: LICENSE
Keywords: decrypt,encryption,libreoffice,odf,odp,ods,odt,opendocument,openoffice,password
Classifier: Development Status :: 4 - Beta
Classifier: Intended Audience :: Developers
Classifier: License :: OSI Approved :: Apache Software License
Classifier: Operating System :: OS Independent
Classifier: Programming Language :: Python :: 3
Classifier: Programming Language :: Python :: 3.10
Classifier: Programming Language :: Python :: 3.11
Classifier: Programming Language :: Python :: 3.12
Classifier: Programming Language :: Python :: 3.13
Classifier: Programming Language :: Python :: 3.14
Classifier: Topic :: Security :: Cryptography
Classifier: Topic :: Software Development :: Libraries :: Python Modules
Classifier: Typing :: Typed
Requires-Python: >=3.10
Requires-Dist: argon2-cffi>=25.1.0
Requires-Dist: cryptography>=44.0.0
Requires-Dist: pycryptodome>=3.21.0
